meoBook/__init__.py
meoBook/meobook.py
meobook-0.0.9.dist-info/METADATA
meobook-0.0.9.dist-info/WHEEL
meobook-0.0.9.dist-info/top_level.txt
meobook-0.0.9.dist-info/RECORD
