Metadata-Version: 2.1
Name: meobook
Version: 0.0.9
Summary: Module to search and download a book from the internet
Home-page: https://github.com/Tina-rt/meobook
Author: Tina Ratolojanahary
Author-email: <rtinahubert@gmail.com>
License: UNKNOWN
Project-URL: Github, https://github.com/Tina-rt/meobook
Keywords: module to download pdf ,python download book,pdf downloader,book search engine module
Platform: UNKNOWN
Classifier: Development Status :: 3 - Alpha
Classifier: Intended Audience :: Education
Classifier: Programming Language :: Python :: 2
Classifier: Programming Language :: Python :: 3
Classifier: Operating System :: MacOS :: MacOS X
Classifier: Operating System :: Microsoft :: Windows
Requires-Dist: bs4
Requires-Dist: requests
